friendlydateparser/__init__.py
friendlydateparser/tz_abbreviations.py
friendlydateparser/antlr/FriendlyDateLexer.py
friendlydateparser/antlr/FriendlyDateParser.py
friendlydateparser/antlr/FriendlyDateVisitor.py
friendlydateparser/antlr/FriendlyDateVisitorPy.py
friendlydateparser-0.2.4.dist-info/LICENSE
friendlydateparser-0.2.4.dist-info/WHEEL
friendlydateparser-0.2.4.dist-info/METADATA
friendlydateparser-0.2.4.dist-info/RECORD
