Metadata-Version: 2.1
Name: friendlydateparser
Version: 0.2.4
Summary: A flexible date parsing library that can handle complex natural language expressions, making date manipulation easy and intuitive.
Keywords: date parsing,natural language,calendar,flexible dates,utility,date,parser
Author-email: Salvador Fandiño García <sfandino@yahoo.com>
Requires-Dist: antlr4-python3-runtime >= 4.13
Requires-Dist: python-dateutil >= 2.8
Requires-Dist: pytz >= 2024
Project-URL: Source, https://github.com/salva/py-friendlydateparser
